FlaskerUtil.py
FlaskerUtil-0.1.0.dist-info/LICENSE.txt
FlaskerUtil-0.1.0.dist-info/METADATA
FlaskerUtil-0.1.0.dist-info/WHEEL
FlaskerUtil-0.1.0.dist-info/top_level.txt
FlaskerUtil-0.1.0.dist-info/RECORD
