Metadata-Version: 2.1
Name: FlaskerUtil
Version: 0.1.0
Summary: Utils to support SQLLite and Flask connectivity
Author: Flask
Classifier: Programming Language :: Python :: 3
Classifier: License :: OSI Approved :: MIT License
Classifier: Operating System :: OS Independent
Requires-Python: >=3.6
License-File: LICENSE.txt
Requires-Dist: pandas
Requires-Dist: numpy
